ABBRobotEGM/__init__.py
ABBRobotEGM/abb_data.py
ABBRobotEGM/egm.py
ABBRobotEGM/_egm_protobuf/__init__.py
ABBRobotEGM/_egm_protobuf/egm_pb2.py
abbrobotegm-1.0.4.dist-info/licenses/LICENSE
abbrobotegm-1.0.4.dist-info/METADATA
abbrobotegm-1.0.4.dist-info/WHEEL
abbrobotegm-1.0.4.dist-info/top_level.txt
abbrobotegm-1.0.4.dist-info/RECORD
