Metadata-Version: 2.4
Name: ABBRobotEGM
Version: 1.0.4
Summary: A Python library for real-time control and data streaming of ABB robots using EGM protocol, enabling high-frequency (250Hz) communication through UDP for industrial automation applications.
Home-page: https://github.com/FLo-ABB/ABB-EGM-Python
Author: Florian LOBERT
Classifier: Programming Language :: Python :: 3
Classifier: License :: OSI Approved :: Apache Software License
Classifier: Operating System :: OS Independent
Classifier: Intended Audience :: Developers
Requires-Python: >=3.6
License-File: LICENSE
Requires-Dist: numpy
Requires-Dist: protobuf
Dynamic: author
Dynamic: classifier
Dynamic: description
Dynamic: description-content-type
Dynamic: home-page
Dynamic: license-file
Dynamic: requires-dist
Dynamic: requires-python
Dynamic: summary
